objdet/__about__.py
objdet/__init__.py
objdet/YOLOV8/__init__.py
objdet/YOLOV8/make_arch.ipynb
objdet/YOLOV8/yolo.py
objdet/YOLOV8/nn/modules/__init__.py
objdet/YOLOV8/nn/modules/block.py
objdet/YOLOV8/nn/modules/conv.py
objdet/YOLOV8/nn/modules/head.py
objdet/YOLOV8/utils/__init__.py
objdet/YOLOV8/utils/tal.py
objdet-0.0.1.dist-info/METADATA
objdet-0.0.1.dist-info/WHEEL
objdet-0.0.1.dist-info/licenses/LICENSE.txt
objdet-0.0.1.dist-info/RECORD
